simplea
